{
	"users": [
		{
			"username": "stacykim",
			"firstname": "Stacy",
			"lastname": "Kim",
			"email": "spk004@ucsd.edu",
			"houseID": "0",
			"password": "roommate1",
			"id": "0",
			"events": [
				"trash",
				"parking",
				"cleaning"
			]
		},
		{
			"username": "alyssaramiro",
			"firstname": "Alyssa",
			"lastname": "Ramiro",
			"email": "aramiro@ucsd.edu",
			"houseID": "0",
			"id": "1",
			"password": "roommate2"
		},
		{
			"username": "apurwashulka",
			"firstname": "Apurwa",
			"lastname": "Shulka",
			"email": "aashukla@ucsd.edu",
			"houseID": "0",
			"id": "2",
			"password": "roommate3"
		},
		{
			"username": "user",
			"firstname": "user",
			"lastname": "last",
			"email": "user@ucsd.edu",
			"houseID": "0",
			"id": "3",
			"password": "roommate4",
			"events": [
				"Trash",
				"Parking",
				"Cleaning"
			]
		}
	],
	"households": [
		{
			"houseID": "0",
			"houseCode": "first",
			"members": [
				{
					"id": "0"
				},
				{
					"id": "1"
				},
				{
					"id": "2"
				},
				{
					"id": "3"
				}
			],
			"events": [
				"dishes",
				"parking",
				"cleaning",
				""
			],
			"shared": []

		}
	]
}